openpack_torch/__init__.py
openpack_torch/configs/__init__.py
openpack_torch/configs/_hydra.py
openpack_torch/configs/datasets.py
openpack_torch/data/__init__.py
openpack_torch/data/_baseclass.py
openpack_torch/data/_wrapper.py
openpack_torch/data/datamodule.py
openpack_torch/data/datasets.py
openpack_torch/data/preprocessing.py
openpack_torch/data/utils.py
openpack_torch/lightning.py
openpack_torch/models/__init__.py
openpack_torch/models/imu/__init__.py
openpack_torch/models/imu/deep_conv_lstm.py
openpack_torch/models/imu/unet.py
openpack_torch/models/keypoint/__init__.py
openpack_torch/models/keypoint/graph.py
openpack_torch/models/keypoint/stgcn.py
openpack_torch/utils/__init__.py
openpack_torch/utils/random.py
openpack_torch/utils/test_helper.py
openpack_torch-1.0.1.dist-info/LICENSE
openpack_torch-1.0.1.dist-info/WHEEL
openpack_torch-1.0.1.dist-info/METADATA
openpack_torch-1.0.1.dist-info/RECORD
