Metadata-Version: 2.1
Name: openpack-torch
Version: 1.0.1
Summary: PyTorch extention to work around with OpenPack dataset
Home-page: https://open-pack.github.io/home
License: MIT
Author: Yoshimura Naoya
Author-email: yoshimura.naoya@ist.osaka-u.ac.jp
Requires-Python: >=3.8,<4.0
Classifier: License :: OSI Approved :: MIT License
Classifier: Programming Language :: Python :: 3
Classifier: Programming Language :: Python :: 3.8
Classifier: Programming Language :: Python :: 3.9
Requires-Dist: hydra-core (>=1.3.1,<2.0.0)
Requires-Dist: numpy (>=1.22.3,<2.0.0)
Requires-Dist: omegaconf (>=2.3.0,<3.0.0)
Requires-Dist: openpack-toolkit (==1.0.1)
Requires-Dist: pandas (>=1.5.2,<2.0.0)
Requires-Dist: pytorch-lightning (>=2.1,<3.0)
Requires-Dist: torch (>=2.1,<3.0)
Requires-Dist: tqdm (>=4.64.1,<5.0.0)
Project-URL: Repository, https://github.com/open-pack/openpack-torch
